demo_kawaki/__init__.py
demo_kawaki/admin.py
demo_kawaki/apps.py
demo_kawaki/models.py
demo_kawaki/tests.py
demo_kawaki/urls.py
demo_kawaki/views.py
demo_kawaki/migrations/__init__.py
demo_kawaki/templates/demo_kawaki/index.html
demo_kawaki-0.1.1.dist-info/METADATA
demo_kawaki-0.1.1.dist-info/WHEEL
demo_kawaki-0.1.1.dist-info/top_level.txt
demo_kawaki-0.1.1.dist-info/RECORD
